[{
    "title":"Work out everyday",
    "last_check":"success",
    "best_streak":7,
    "successes":11,
    "last_check_date":"2025-06-22",
    "current_streak":7,
    "fails":1
  },{
    "title":"Do breathing exercise",
    "last_check":"success",
    "best_streak":7,
    "successes":11,
    "last_check_date":"2025-06-22",
    "current_streak":7,
    "fails":1
  },{
    "title":"Meditate",
    "last_check":"fail",
    "best_streak":3,
    "successes":6,
    "last_check_date":"2025-06-22",
    "current_streak":0,
    "fails":6
  },{
    "title":"Eat healthy",
    "last_check":"success",
    "best_streak":8,
    "successes":10,
    "last_check_date":"2025-06-22",
    "current_streak":8,
    "fails":2
  },{
    "title":"Don't do drugs",
    "last_check":"fail",
    "best_streak":7,
    "successes":10,
    "last_check_date":"2025-06-22",
    "current_streak":0,
    "fails":2
  },{
    "title":"Don't masturbate",
    "last_check":"fail",
    "best_streak":6,
    "successes":10,
    "last_check_date":"2025-06-22",
    "current_streak":0,
    "fails":2
  },{
    "title":"No video-games",
    "last_check":"success",
    "best_streak":12,
    "successes":12,
    "last_check_date":"2025-06-22",
    "current_streak":12,
    "fails":0
  },{
    "title":"Code everyday",
    "last_check":"success",
    "best_streak":12,
    "successes":12,
    "last_check_date":"2025-06-22",
    "current_streak":12,
    "fails":0
  }]