[{
    "successes":40,
    "current_streak":11,
    "fails":5,
    "last_check_date":"2025-07-25",
    "best_streak":13,
    "title":"Work out everyday",
    "last_check":"success"
  },{
    "successes":31,
    "current_streak":2,
    "fails":14,
    "last_check_date":"2025-07-25",
    "best_streak":13,
    "title":"Do breathing exercise",
    "last_check":"success"
  },{
    "successes":20,
    "current_streak":3,
    "fails":25,
    "last_check_date":"2025-07-25",
    "best_streak":3,
    "title":"Meditate",
    "last_check":"success"
  },{
    "successes":32,
    "current_streak":3,
    "fails":13,
    "last_check_date":"2025-07-25",
    "best_streak":9,
    "title":"Eat healthy",
    "last_check":"success"
  },{
    "successes":31,
    "current_streak":2,
    "fails":14,
    "last_check_date":"2025-07-25",
    "best_streak":7,
    "title":"Don't do drugs",
    "last_check":"success"
  },{
    "successes":32,
    "current_streak":1,
    "fails":13,
    "last_check_date":"2025-07-25",
    "best_streak":6,
    "title":"Don't masturbate",
    "last_check":"success"
  },{
    "successes":40,
    "current_streak":0,
    "fails":5,
    "last_check_date":"2025-07-25",
    "best_streak":23,
    "title":"No video-games",
    "last_check":"fail"
  },{
    "successes":40,
    "current_streak":4,
    "fails":5,
    "last_check_date":"2025-07-25",
    "best_streak":18,
    "title":"Code everyday",
    "last_check":"success"
  },{
    "successes":2,
    "current_streak":0,
    "fails":31,
    "last_check_date":"2025-07-25",
    "best_streak":1,
    "title":"Don't smoke",
    "last_check":"fail"
  },{
    "successes":21,
    "current_streak":3,
    "fails":4,
    "last_check_date":"2025-07-25",
    "best_streak":12,
    "title":"Dont' waste time on youtube",
    "last_check":"success"
  },{
    "successes":14,
    "current_streak":14,
    "fails":1,
    "last_check_date":"2025-07-25",
    "best_streak":14,
    "title":"Stop scrolling reddit",
    "last_check":"success"
  }]